depot/__init__.py
depot/apt.py
depot/gpg.py
depot/repository.py
depot/storage.py
depot/utils.py
depot/version.py
depot/yum/__init__.py
depot/yum/base.py
depot/yum/filelists.py
depot/yum/other.py
depot/yum/primary.py
depot/yum/repomd.py
depot-0.0.12.data/scripts/depot
depot-0.0.12.dist-info/DESCRIPTION.rst
depot-0.0.12.dist-info/entry_points.txt
depot-0.0.12.dist-info/METADATA
depot-0.0.12.dist-info/pydist.json
depot-0.0.12.dist-info/RECORD
depot-0.0.12.dist-info/top_level.txt
depot-0.0.12.dist-info/WHEEL
