Metadata-Version: 2.0
Name: depot
Version: 0.0.12
Summary: Manage package repositories in the cloud.
Home-page: http://github.com/coderanger/depot
Author: Noah Kantrowitz
Author-email: noah@coderanger.net
License: Apache 2.0
Platform: UNKNOWN
Classifier: Development Status :: 4 - Beta
Classifier: License :: OSI Approved :: Apache Software License
Classifier: Natural Language :: English
Classifier: Operating System :: OS Independent
Classifier: Programming Language :: Python
Requires-Dist: apache-libcloud (>=0.14.0)
Requires-Dist: docopt
Requires-Dist: six
Requires-Dist: lockfile
Requires-Dist: arpy
Requires-Dist: python-gnupg
Requires-Dist: defusedxml
Requires-Dist: lxml
